Metadata-Version: 1.0
Name: htsql-xport
Version: 0.1.1
Summary: An HTSQL extension that adds basic SAS V5 XPORT transport file support.
Home-page: https://bitbucket.org/prometheus/htsql_xport
Author: Prometheus Research, LLC
Author-email: UNKNOWN
License: AGPLv3
Platform: UNKNOWN
